<ZT2Strings>
      <LOC_STRING _locID="zoopedia_savannahrocks:entry"  >Savannah Rocks</LOC_STRING>
      <LOC_STRING _locID="zoopedia_savannahrocks:text"  >
         <cell pady="0" width="1000"/>
         <p/>
         <cell width="260"/>
         <cell width="640" height="320" bgimg="ui/zoopedia/topCellBg.dds">
            <cell width="600" padx="20" pady="20">
               <color r="255" g="255" b="255">
                  <img src="entities/objects/rocks/savannah/Rock_Savannah_Small_icon.dds" sx="0" sy="0" sw="64" sh="64"/>
                  <img src="entities/objects/rocks/savannah/Rock_Savannah_Medium_icon.dds" sx="0" sy="0" sw="64" sh="64"/>
                  <img src="entities/objects/rocks/savannah/Rock_Savannah_Large_icon.dds" sx="0" sy="0" sw="64" sh="64"/>
                  <p/>
                  
                  
                  
				Savannah rocks are appropriate for exhibits that contain savannah animals, including the elephant, zebra, and lion. 
				They can also be used in public areas that are savannah-themed.
				
               
               
               </color>
            </cell>
         </cell>
      </LOC_STRING>
      <LOC_STRING _locID="zoopedia_rainforestrocks:entry"  >Rainforest Rocks</LOC_STRING>
      <LOC_STRING _locID="zoopedia_rainforestrocks:text"  >
         <cell pady="0" width="1000"/>
         <p/>
         <cell width="260"/>
         <cell width="640" height="320" bgimg="ui/zoopedia/topCellBg.dds">
            <cell width="600" padx="20" pady="20">
               <color r="255" g="255" b="255">
                  <img src="entities/objects/rocks/tropicalrainforest/Rock_TropicalRainforest_Small_icon.dds" sx="0" sy="0" sw="64" sh="64"/>
                  <img src="entities/objects/rocks/tropicalrainforest/Rock_TropicalRainforest_Medium_icon.dds" sx="0" sy="0" sw="64" sh="64"/>
                  <img src="entities/objects/rocks/tropicalrainforest/Rock_TropicalRainforest_Large_icon.dds" sx="0" sy="0" sw="64" sh="64"/>
                  <p/>
                  
                  
                  
				Rainforest rocks are appropriate for exhibits that contain rainforest animals, including the gorilla and tiger. 
				They can also be used in public areas that are rainforest-themed.
				
               
               
               </color>
            </cell>
         </cell>
      </LOC_STRING>
      <LOC_STRING _locID="zoopedia_borealrocks:entry"  >Boreal Forest Rocks</LOC_STRING>
      <LOC_STRING _locID="zoopedia_borealrocks:text"  >
         <cell pady="0" width="1000"/>
         <p/>
         <cell width="260"/>
         <cell width="640" height="320" bgimg="ui/zoopedia/topCellBg.dds">
            <cell width="600" padx="20" pady="20">
               <color r="255" g="255" b="255">
                  <img src="entities/objects/rocks/borealforest/Rock_BorealForest_Small_icon.dds" sx="0" sy="0" sw="64" sh="64"/>
                  <img src="entities/objects/rocks/borealforest/Rock_BorealForest_Medium_icon.dds" sx="0" sy="0" sw="64" sh="64"/>
                  <img src="entities/objects/rocks/borealforest/Rock_BorealForest_Large_icon.dds" sx="0" sy="0" sw="64" sh="64"/>
                  <p/>
                  
                  
                                 
               Boreal forest rocks are compatible with exhibits that contain boreal forest foliage, 
               including the 
		     
                  
                  
                  <a href="zoopedia:zoopedia_fringedpolygala:entry">
                     <u>
                        <color r="255" g="231" b="135">fringed polygala flower</color>
                     </u>
                  </a>
                  
                  
                                  
               , 
		     
                  
                  
                  <a href="zoopedia:zoopedia_reindeerlichen:entry">
                     <u>
                        <color r="255" g="231" b="135">reindeer lichen</color>
                     </u>
                  </a>
                  
                  
                                  
               , and the 
		     
                  
                  
                  <a href="zoopedia:zoopedia_balsamfir:entry">
                     <u>
                        <color r="255" g="231" b="135">balsam fir</color>
                     </u>
                  </a>
                  
                  
                                  
               ,
		     
                  
                  
                  <a href="zoopedia:zoopedia_blackspruce:entry">
                     <u>
                        <color r="255" g="231" b="135">black spruce</color>
                     </u>
                  </a>
                  
                  
                                  
               , and 
		     
                  
                  
                  <a href="zoopedia:zoopedia_tamarack:entry">
                     <u>
                        <color r="255" g="231" b="135">tamarack </color>
                     </u>
                  </a>
                  
                  
                                  
                trees.
				
               
               
               </color>
            </cell>
         </cell>
      </LOC_STRING>
      <LOC_STRING _locID="zoopedia_alpinerocks:entry"  >Alpine Rocks</LOC_STRING>
      <LOC_STRING _locID="zoopedia_alpinerocks:text"  >
         <cell pady="0" width="1000"/>
         <p/>
         <cell width="260"/>
         <cell width="640" height="320" bgimg="ui/zoopedia/topCellBg.dds">
            <cell width="600" padx="20" pady="20">
               <color r="255" g="255" b="255">
                  <img src="entities/objects/rocks/alpine/Rock_Alpine_Small_icon.dds" sx="0" sy="0" sw="64" sh="64"/>
                  <img src="entities/objects/rocks/alpine/Rock_Alpine_Medium_icon.dds" sx="0" sy="0" sw="64" sh="64"/>
                  <img src="entities/objects/rocks/alpine/Rock_Alpine_Large_icon.dds" sx="0" sy="0" sw="64" sh="64"/>
                  <p/>
                  
                  
                  
               Alpine rocks are appropriate for exhibits that contain alpine foliage, 
               including 
		     
                  
                  
                  <a href="zoopedia:zoopedia_larkspur:entry">
                     <u>
                        <color r="255" g="231" b="135">larkspur</color>
                     </u>
                  </a>
                  
                  
                   
               , the 
		     
                  
                  
                  <a href="zoopedia:zoopedia_yellowcedar:entry">
                     <u>
                        <color r="255" g="231" b="135">yellow cedar </color>
                     </u>
                  </a>
                  
                  
                   
                tree, and the 
		     
                  
                  
                  <a href="zoopedia:zoopedia_himalayanbirch:entry">
                     <u>
                        <color r="255" g="231" b="135">Himalayan birch </color>
                     </u>
                  </a>
                  
                  
                                  
                 and 
		     
                  
                  
                  <a href="zoopedia:zoopedia_himalayanpine:entry">
                     <u>
                        <color r="255" g="231" b="135">Himalayan pine </color>
                     </u>
                  </a>
                  
                  
                                   
		 trees.
				
               
               
               </color>
            </cell>
         </cell>
      </LOC_STRING>
      <LOC_STRING _locID="zoopedia_scrubrocks:entry"  >Scrub Rocks</LOC_STRING>
      <LOC_STRING _locID="zoopedia_scrubrocks:text"  >
         <cell pady="0" width="1000"/>
         <p/>
         <cell width="260"/>
         <cell width="640" height="320" bgimg="ui/zoopedia/topCellBg.dds">
            <cell width="600" padx="20" pady="20">
               <color r="255" g="255" b="255">
                  <img src="entities/objects/rocks/scrub/Rock_Scrub_Small_icon.dds" sx="0" sy="0" sw="64" sh="64"/>
                  <img src="entities/objects/rocks/scrub/Rock_Scrub_Medium_icon.dds" sx="0" sy="0" sw="64" sh="64"/>
                  <img src="entities/objects/rocks/scrub/Rock_Scrub_Large_icon.dds" sx="0" sy="0" sw="64" sh="64"/>
                  <p/>
                  
                  
                  
               Scrub rocks are appropriate for exhibits that contain scrub animals, including the kangaroo and gemsbok. 
               They can also be used in public areas that are scrub-themed.
				
               
               
               </color>
            </cell>
         </cell>
      </LOC_STRING>
      <LOC_STRING _locID="zoopedia_desertrocks:entry"  >Desert Rocks</LOC_STRING>
      <LOC_STRING _locID="zoopedia_desertrocks:text"  >
         <cell pady="0" width="1000"/>
         <p/>
         <cell width="260"/>
         <cell width="640" height="320" bgimg="ui/zoopedia/topCellBg.dds">
            <cell width="600" padx="20" pady="20">
               <color r="255" g="255" b="255">
                  <img src="entities/objects/rocks/desert/Rock_Desert_Small_icon.dds" sx="0" sy="0" sw="64" sh="64"/>
                  <img src="entities/objects/rocks/desert/Rock_Desert_Medium_icon.dds" sx="0" sy="0" sw="64" sh="64"/>
                  <img src="entities/objects/rocks/desert/Rock_Desert_Large_icon.dds" sx="0" sy="0" sw="64" sh="64"/>
                  <p/>
                  
                  
                  
               Desert rocks are appropriate for exhibits that contain desert animals, including the camel. 
               They can also be used in public areas that are desert-themed.
				
               
               
               </color>
            </cell>
         </cell>
      </LOC_STRING>
      <LOC_STRING _locID="zoopedia_wetlandrocks:entry"  >Wetland Rocks</LOC_STRING>
      <LOC_STRING _locID="zoopedia_wetlandrocks:text"  >
         <cell pady="0" width="1000"/>
         <p/>
         <cell width="260"/>
         <cell width="640" height="320" bgimg="ui/zoopedia/topCellBg.dds">
            <cell width="600" padx="20" pady="20">
               <color r="255" g="255" b="255">
                  <img src="entities/objects/rocks/wetlands/Rock_Wetlands_Small_icon.dds" sx="0" sy="0" sw="64" sh="64"/>
                  <img src="entities/objects/rocks/wetlands/Rock_Wetlands_Medium_icon.dds" sx="0" sy="0" sw="64" sh="64"/>
                  <img src="entities/objects/rocks/wetlands/Rock_Wetlands_Large_icon.dds" sx="0" sy="0" sw="64" sh="64"/>
                  <p/>
                  
                  
                  
               Wetland rocks are appropriate for exhibits that contain wetland animals, including the hippo, crocodile, and flamingo. 
               They can also be used in public areas that are wetland-themed.
				
               
               
               </color>
            </cell>
         </cell>
      </LOC_STRING>
      <LOC_STRING _locID="zoopedia_tundrarocks:entry"  >Tundra Rocks</LOC_STRING>
      <LOC_STRING _locID="zoopedia_tundrarocks:text"  >
         <cell pady="0" width="1000"/>
         <p/>
         <cell width="260"/>
         <cell width="640" height="320" bgimg="ui/zoopedia/topCellBg.dds">
            <cell width="600" padx="20" pady="20">
               <color r="255" g="255" b="255">
                  <img src="entities/objects/rocks/tundra/Rock_Tundra_Small_icon.dds" sx="0" sy="0" sw="64" sh="64"/>
                  <img src="entities/objects/rocks/tundra/Rock_Tundra_Medium_icon.dds" sx="0" sy="0" sw="64" sh="64"/>
                  <img src="entities/objects/rocks/tundra/Rock_Tundra_Large_icon.dds" sx="0" sy="0" sw="64" sh="64"/>
                  <p/>
                  
                  
                  
               Tundra rocks are appropriate for exhibits that contain tundra animals, including the polar bear and penguin. 
               They can also be used in public areas that are tundra-themed.
				
               
               
               </color>
            </cell>
         </cell>
      </LOC_STRING>
      <LOC_STRING _locID="zoopedia_grasslandrocks:entry"  >Grassland Rocks</LOC_STRING>
      <LOC_STRING _locID="zoopedia_grasslandrocks:text"  >
         <cell pady="0" width="1000"/>
         <p/>
         <cell width="260"/>
         <cell width="640" height="320" bgimg="ui/zoopedia/topCellBg.dds">
            <cell width="600" padx="20" pady="20">
               <color r="255" g="255" b="255">
                  <img src="entities/objects/rocks/grassland/Rock_Grassland_Small_icon.dds" sx="0" sy="0" sw="64" sh="64"/>
                  <img src="entities/objects/rocks/grassland/Rock_Grassland_Medium_icon.dds" sx="0" sy="0" sw="64" sh="64"/>
                  <img src="entities/objects/rocks/grassland/Rock_Grassland_Large_icon.dds" sx="0" sy="0" sw="64" sh="64"/>
                  <p/>
                  
                  
                  
               Grassland rocks are appropriate for exhibits that contain grassland animals. 
               They can also be used in public areas that are grassland-themed.
				
               
               
               </color>
            </cell>
         </cell>
      </LOC_STRING>
      <LOC_STRING _locID="zoopedia_temperaterocks:entry"  >Temperate Forest Rocks</LOC_STRING>
      <LOC_STRING _locID="zoopedia_temperaterocks:text"  >
         <cell pady="0" width="1000"/>
         <p/>
         <cell width="260"/>
         <cell width="640" height="320" bgimg="ui/zoopedia/topCellBg.dds">
            <cell width="600" padx="20" pady="20">
               <color r="255" g="255" b="255">
                  <img src="entities/objects/rocks/temperateforest/Rock_TemperateForest_Small_icon.dds" sx="0" sy="0" sw="64" sh="64"/>
                  <img src="entities/objects/rocks/temperateforest/Rock_TemperateForest_Medium_icon.dds" sx="0" sy="0" sw="64" sh="64"/>
                  <img src="entities/objects/rocks/temperateforest/Rock_TemperateForest_Large_icon.dds" sx="0" sy="0" sw="64" sh="64"/>
                  <p/>
                  
                  
                  
               Temperate forest rocks are appropriate for exhibits that contain temperate forest animals, including the giant panda, red panda, and common peafowl. 
               They can also be used in public areas that are temperate forest-themed.
				
               
               
               </color>
            </cell>
         </cell>
      </LOC_STRING>
</ZT2Strings>
