<ZT2Strings>
      <LOC_STRING _locID="entityname:bathroomlarge_et">Banheiro familiar</LOC_STRING>
      <LOC_STRING _locID="entityname:bathroomlarge_et_stt">Banheiro familiar</LOC_STRING>
      <LOC_STRING _locID="entityname:bathroomlarge_et_lower">o banheiro familiar</LOC_STRING>
      <LOC_STRING _locID="entityname:bathroomlarge_et_ltt">
		   <color r="255" g="248" b="178">
		      <b>Banheiro familiar</b>
		   </color>
		   <br/>
		   Selecione e posicione o banheiro familiar. Seu custo é superior ao de um banheiro pequeno, mas ele tem espaço para seis pessoas a mais.
      </LOC_STRING>
      <LOC_STRING _locID="entityname:bathroomsmall_et">Banheiro pequeno</LOC_STRING>
      <LOC_STRING _locID="entityname:bathroomsmall_et_stt">Banheiro pequeno</LOC_STRING>
      <LOC_STRING _locID="entityname:bathroomsmall_et_lower">o banheiro pequeno</LOC_STRING>
      <LOC_STRING _locID="entityname:bathroomsmall_et_ltt">
         <color r="255" g="248" b="178">
            <b>Banheiro pequeno</b>
         </color>
         <br/>
         Clique para selecionar e posicionar o banheiro pequeno, que pode acomodar um visitante de cada vez.
      </LOC_STRING>
      <LOC_STRING _locID="entityname:foodstand_burger_et">Quiosque de hambúrguer</LOC_STRING>
      <LOC_STRING _locID="entityname:foodstand_burger_et_stt">Quiosque de hambúrguer</LOC_STRING>
      <LOC_STRING _locID="entityname:foodstand_burger_et_lower">o quiosque de hambúrguer</LOC_STRING>
      <LOC_STRING _locID="entityname:foodstand_burger_et_ltt">
		         <color r="255" g="248" b="178">
		            <b>Quiosque de hambúrguer</b>
		         </color>
		         <br/>
		         Clique para selecionar e posicionar o quiosque de hambúrguer. Os hambúrgueres têm um preço razoável e matam razoavelmente a fome.     
      </LOC_STRING>
      <LOC_STRING _locID="entityname:foodstand_hotdog_et">Quiosque de cachorro-quente</LOC_STRING>
      <LOC_STRING _locID="entityname:foodstand_hotdog_et_stt">Quiosque de cachorro-quente</LOC_STRING>
      <LOC_STRING _locID="entityname:foodstand_hotdog_et_lower">o quiosque de cachorro-quente</LOC_STRING>
      <LOC_STRING _locID="entityname:foodstand_hotdog_et_ltt">
         <color r="255" g="248" b="178">
            <b>Quiosque: cachorro-quente</b>
         </color>
         <br/>
         Clique para selecionar e posicionar o quiosque de cachorro-quente.
Prato tipicamente americano, o cachorro-quente é um dos lanches favoritos das crianças.
      </LOC_STRING>
      <LOC_STRING _locID="entityname:foodstand_salad_et">Quiosque de saladas</LOC_STRING>
      <LOC_STRING _locID="entityname:foodstand_salad_et_stt">Quiosque de saladas</LOC_STRING>
      <LOC_STRING _locID="entityname:foodstand_salad_et_lower">o quiosque de saladas</LOC_STRING>
      <LOC_STRING _locID="entityname:foodstand_salad_et_ltt">
		         <color r="255" g="248" b="178">
		            <b>Quiosque de saladas</b>
		         </color>
		         <br/>
		         Clique para selecionar e posicionar o quiosque de saladas.
		 Em geral as crianças não gostam muito de saladas, mas os adultos adoram.
      </LOC_STRING>
      <LOC_STRING _locID="entityname:foodstand_soda_et">Quiosque de refrigerante</LOC_STRING>
      <LOC_STRING _locID="entityname:foodstand_soda_et_stt">Quiosque de refrigerante</LOC_STRING>
      <LOC_STRING _locID="entityname:foodstand_soda_et_lower">o quiosque de refrigerante</LOC_STRING>
      <LOC_STRING _locID="entityname:foodstand_soda_et_ltt">
         <color r="255" g="248" b="178">
            <b>Quiosque de refrigerante</b>
         </color>
         <br/>
          Clique para selecionar e posicionar o quiosque de refrigerante. Refrigerantes são a bebida preferida da maioria dos visitantes do zoológico. 
      </LOC_STRING>
      <LOC_STRING _locID="entityname:foodstand_sub_et">Quiosque de sanduíche</LOC_STRING>
      <LOC_STRING _locID="entityname:foodstand_sub_et_stt">Quiosque de sanduíche</LOC_STRING>
      <LOC_STRING _locID="entityname:foodstand_sub_et_lower">o quiosque de sanduíche</LOC_STRING>
      <LOC_STRING _locID="entityname:foodstand_sub_et_ltt">
         <color r="255" g="248" b="178">
            <b>Quiosque de sanduíche</b>
         </color>
         <br/>
          Clique para selecionar e posicionar o quiosque de sanduíche. Estes sanduíches de carne são muito procurados no horário de almoço.
 
      </LOC_STRING>
      <LOC_STRING _locID="entityname:foodstand_sushi_et">Quiosque de sushi</LOC_STRING>
      <LOC_STRING _locID="entityname:foodstand_sushi_et_stt">Quiosque de sushi</LOC_STRING>
      <LOC_STRING _locID="entityname:foodstand_sushi_et_lower">o quiosque de sushi</LOC_STRING>
      <LOC_STRING _locID="entityname:foodstand_sushi_et_ltt">
         <color r="255" g="248" b="178">
            <b>Quiosque de sushi</b>
         </color>
         <br/>
          Clique para selecionar e posicionar o quiosque de sushi. Trata-se de um prato caro e mais apreciado pelos adultos do que pelas crianças. 
      </LOC_STRING>
      <LOC_STRING _locID="entityname:foodstand_water_et">Quiosque de água</LOC_STRING>
      <LOC_STRING _locID="entityname:foodstand_water_et_stt">Quiosque de água</LOC_STRING>
      <LOC_STRING _locID="entityname:foodstand_water_et_lower">o quiosque de água</LOC_STRING>
      <LOC_STRING _locID="entityname:foodstand_water_et_ltt">
         <color r="255" g="248" b="178">
            <b>Quiosque de água</b>
         </color>
         <br/>
          Clique para selecionar e posicionar o quiosque de água.
  A água atenderá às necessidades básicas dos visitantes no que diz respeito à sede.    
 
      </LOC_STRING>
      <LOC_STRING _locID="entityname:foodstand_shishkabob_et">Quiosque de shish-kebab</LOC_STRING>
      <LOC_STRING _locID="entityname:foodstand_shishkabob_et_stt">Quiosque de shish-kebab</LOC_STRING>
      <LOC_STRING _locID="entityname:foodstand_shishkabob_et_lower">o quiosque de shish-kebab</LOC_STRING>
      <LOC_STRING _locID="entityname:foodstand_shishkabob_et_ltt">
         <color r="255" g="248" b="178">
            <b>Quiosque de shish-kebab</b>
         </color>
         <br/>
          Clique para selecionar e posicionar o quiosque de shish-kebab, que oferece um alimento rico em proteína por um preço razoável.
 
      </LOC_STRING>
      <LOC_STRING _locID="entityname:foodstand_coffee_et">Quiosque de café</LOC_STRING>
      <LOC_STRING _locID="entityname:foodstand_coffee_et_stt">Quiosque de café</LOC_STRING>
      <LOC_STRING _locID="entityname:foodstand_coffee_et_lower">o quiosque de café</LOC_STRING>
      <LOC_STRING _locID="entityname:foodstand_coffee_et_ltt">
         <color r="255" g="248" b="178">
            <b>Quiosque de café</b>
         </color>
         <br/>
          Clique para selecionar e posicionar o quiosque de café. Os adultos adoram a energia da cafeína, e alguns jovens também estão dispostos a experimentá-la.
      </LOC_STRING>
      <LOC_STRING _locID="entityname:snackcart_cheesecake_et">Carrinho de cheesecake</LOC_STRING>
      <LOC_STRING _locID="entityname:snackcart_cheesecake_et_stt">Carrinho de cheesecake</LOC_STRING>
      <LOC_STRING _locID="entityname:snackcart_cheesecake_et_lower">o carrinho de cheesecake</LOC_STRING>
      <LOC_STRING _locID="entityname:snackcart_cheesecake_et_ltt">
         <color r="255" g="248" b="178">
            <b>Carrinho de cheesecake</b>
         </color>
         <br/>
         Clique para selecionar e posicionar o carrinho de cheesecake, uma sobremesa muito apreciada pelos adultos.
      </LOC_STRING>
      <LOC_STRING _locID="entityname:snackcart_popcorn_et">Carrinho de pipoca</LOC_STRING>
      <LOC_STRING _locID="entityname:snackcart_popcorn_et_stt">Carrinho de pipoca</LOC_STRING>
      <LOC_STRING _locID="entityname:snackcart_popcorn_et_lower">o carrinho de pipoca</LOC_STRING>
      <LOC_STRING _locID="entityname:snackcart_popcorn_et_ltt">
         <color r="255" g="248" b="178">
            <b>Carrinho de pipoca</b>
         </color>
         <br/>
          Clique para selecionar e posicionar o carrinho de pipoca. A pipoca dá uma sensação de saciação e pode deixar os visitantes com sede.
      </LOC_STRING>
      <LOC_STRING _locID="entityname:snackcart_pretzel_et">Carrinho de pretzel</LOC_STRING>
      <LOC_STRING _locID="entityname:snackcart_pretzel_et_stt">Carrinho de pretzel</LOC_STRING>
      <LOC_STRING _locID="entityname:snackcart_pretzel_et_lower">o carrinho de pretzel</LOC_STRING>
      <LOC_STRING _locID="entityname:snackcart_pretzel_et_ltt">
         <color r="255" g="248" b="178">
            <b>Carrinho de pretzel</b>
         </color>
         <br/>
          Clique para selecionar e posicionar o carrinho de pretzel. Os visitantes podem ficar com sede depois de comer pretzels.   
      </LOC_STRING>
      <LOC_STRING _locID="entityname:snackcart_cottoncandy_et">Carrinho de algodão-doce</LOC_STRING>
      <LOC_STRING _locID="entityname:snackcart_cottoncandy_et_stt">Carrinho de algodão-doce</LOC_STRING>
      <LOC_STRING _locID="entityname:snackcart_cottoncandy_et_lower">o carrinho de algodão-doce</LOC_STRING>
      <LOC_STRING _locID="entityname:snackcart_cottoncandy_et_ltt">
         <color r="255" g="248" b="178">
            <b>Carrinho de algodão-doce</b>
         </color>
         <br/>
          Clique para selecionar e posicionar o carrinho de algodão-doce, um doce tradicional de que as crianças gostam muito.
 
 
      </LOC_STRING>
      <LOC_STRING _locID="entityname:snackcart_fruitcup_et">Carrinho de salada de frutas</LOC_STRING>
      <LOC_STRING _locID="entityname:snackcart_fruitcup_et_stt">Carrinho de salada de frutas</LOC_STRING>
      <LOC_STRING _locID="entityname:snackcart_fruitcup_et_lower">o carrinho de salada de frutas</LOC_STRING>
      <LOC_STRING _locID="entityname:snackcart_fruitcup_et_ltt">
         <color r="255" g="248" b="178">
            <b>Carrinho de salada de frutas</b>
         </color>
         <br/>
          Clique para selecionar e posicionar o carrinho de salada de frutas. Muitos visitantes gostam de saborear frutas como um lanche alternativo saudável.
      </LOC_STRING>
      <LOC_STRING _locID="entityname:snackcart_icecream_et">Carrinho de sorvete</LOC_STRING>
      <LOC_STRING _locID="entityname:snackcart_icecream_et_stt">Carrinho de sorvete</LOC_STRING>
      <LOC_STRING _locID="entityname:snackcart_icecream_et_lower">o carrinho de sorvete</LOC_STRING>
      <LOC_STRING _locID="entityname:snackcart_icecream_et_ltt">
         <color r="255" g="248" b="178">
            <b>Carrinho de sorvete</b>
         </color>
         <br/>
          Clique para selecionar e posicionar o carrinho de sorvete, um dos locais prediletos das crianças no zoológico.
      </LOC_STRING>
      <LOC_STRING _locID="entityname:bench_et">Banco do deserto</LOC_STRING>
      <LOC_STRING _locID="entityname:bench_et_stt">Banco do deserto</LOC_STRING>
      <LOC_STRING _locID="entityname:bench_et_lower">o banco do deserto</LOC_STRING>
      <LOC_STRING _locID="entityname:bench_et_ltt">
		   <color r="255" g="248" b="178">
		      <b>Banco do deserto</b>
		   </color>
		   <br/>
		         Clique para selecionar e posicionar um banco com tema de deserto. Os visitantes gostam de áreas temáticas no zoológico.
      </LOC_STRING>
      <LOC_STRING _locID="entityname:DonationBox_et">Caixa para doações do deserto</LOC_STRING>
      <LOC_STRING _locID="entityname:DonationBox_et_stt">Caixa para doações do deserto</LOC_STRING>
      <LOC_STRING _locID="entityname:DonationBox_et_lower">a caixa para doações do deserto</LOC_STRING>
      <LOC_STRING _locID="entityname:DonationBox_et_ltt">
		   <color r="255" g="248" b="178">
		            <b>Caixa para doações do deserto</b>
		   </color>
		   <br/>
		   Clique para selecionar e posicionar uma caixa para doações com tema de deserto. Espalhe-as por todo o zôo para que os visitantes possam fazer doações.
      </LOC_STRING>
      <LOC_STRING _locID="entityname:umbrellatable_et">Mesa com guarda-sol do deserto</LOC_STRING>
      <LOC_STRING _locID="entityname:umbrellatable_et_stt">Mesa com guarda-sol do deserto</LOC_STRING>
      <LOC_STRING _locID="entityname:umbrellatable_et_lower">a mesa com guarda-sol do deserto</LOC_STRING>
      <LOC_STRING _locID="entityname:umbrellatable_et_ltt">
		   <color r="255" g="248" b="178">
		      <b>Mesa com guarda-sol do deserto</b>
		   </color>
		   <br/>
		         Selecione e posicione uma mesa com guarda-sol com tema de deserto, que proporciona aos visitantes um lugar com sombra para descansar e comer.      
      </LOC_STRING>
      <LOC_STRING _locID="entityname:ViewingArea_et">Cobertura do deserto</LOC_STRING>
      <LOC_STRING _locID="entityname:ViewingArea_et_stt">Cobertura do deserto</LOC_STRING>
      <LOC_STRING _locID="entityname:ViewingArea_et_lower">a cobertura do deserto</LOC_STRING>
      <LOC_STRING _locID="entityname:ViewingArea_et_ltt">
         <color r="255" g="248" b="178">
            <b>Cobertura do deserto</b>
         </color>
         <br/>
         Clique para selecionar e posicionar uma cobertura com tema de deserto, que proporciona aos visitantes um lugar com sombra e conforto para a observação dos animais.
      </LOC_STRING>
      <LOC_STRING _locID="entityname:lamp_et">Poste de luz do deserto</LOC_STRING>
      <LOC_STRING _locID="entityname:lamp_et_stt">Poste de luz do deserto</LOC_STRING>
      <LOC_STRING _locID="entityname:lamp_et_lower">o poste de luz do deserto</LOC_STRING>
      <LOC_STRING _locID="entityname:lamp_et_ltt">
		   <color r="255" g="248" b="178">
		      <b>Poste de luz do deserto</b>
		   </color>
		   <br/>
		         Clique para selecionar e posicionar um poste de luz com tema de deserto. Os visitantes gostam de áreas temáticas no zoológico.
      </LOC_STRING>
      <LOC_STRING _locID="entityname:trashcan_et">Lixeira do deserto</LOC_STRING>
      <LOC_STRING _locID="entityname:trashcan_et_stt">Lixeira do deserto</LOC_STRING>
      <LOC_STRING _locID="entityname:trashcan_et_lower">a lixeira do deserto</LOC_STRING>
      <LOC_STRING _locID="entityname:trashcan_et_ltt">
         <color r="255" g="248" b="178">
            <b>Lixeira do deserto</b>
         </color>
         <br/>
         Selecione e posicione uma lixeira com tema de deserto. Deve haver lixeiras espalhadas por todo o zoológico, para que os visitantes possam jogar o lixo fora.
      </LOC_STRING>
      <LOC_STRING _locID="entityname:Statue_et">Estátua do deserto</LOC_STRING>
      <LOC_STRING _locID="entityname:Statue_et_stt">Estátua do deserto</LOC_STRING>
      <LOC_STRING _locID="entityname:Statue_et_lower">a estátua do deserto</LOC_STRING>
      <LOC_STRING _locID="entityname:Statue_et_ltt">
         <color r="255" g="248" b="178">
            <b>Estátua do deserto</b>
         </color>
         <br/>
         Clique para selecionar e posicionar uma estátua com tema de deserto. Os visitantes costumam apreciar uma estátua bem colocada.
      </LOC_STRING>
      <LOC_STRING _locID="entityname:PathArch_et">Arco do deserto</LOC_STRING>
      <LOC_STRING _locID="entityname:PathArch_et_stt">Arco do deserto</LOC_STRING>
      <LOC_STRING _locID="entityname:PathArch_et_lower">o arco do deserto</LOC_STRING>
      <LOC_STRING _locID="entityname:PathArch_et_ltt">
         <color r="255" g="248" b="178">
            <b>Arco do deserto</b>
         </color>
         <br/>
         Selecione e posicione um arco com tema de deserto, que pode ser um elemento decorativo interessante em trilhas ou entradas nas áreas temáticas do zoológico. 
      </LOC_STRING>
      <LOC_STRING _locID="entityname:Fountain_et">Chafariz do deserto</LOC_STRING>
      <LOC_STRING _locID="entityname:Fountain_et_stt">Chafariz do deserto</LOC_STRING>
      <LOC_STRING _locID="entityname:Fountain_et_lower">o chafariz do deserto</LOC_STRING>
      <LOC_STRING _locID="entityname:Fountain_et_ltt">
         <color r="255" g="248" b="178">
            <b>Chafariz do deserto</b>
         </color>
         <br/>
         Clique para selecionar e posicionar um chafariz com tema de deserto. Os visitantes costumam apreciar um chafariz bem colocado.
      </LOC_STRING>
      <LOC_STRING _locID="entityname:MusicalRock_et">Pedra musical do deserto</LOC_STRING>
      <LOC_STRING _locID="entityname:MusicalRock_et_stt">Pedra musical do deserto</LOC_STRING>
      <LOC_STRING _locID="entityname:MusicalRock_et_lower">a pedra musical do deserto</LOC_STRING>
      <LOC_STRING _locID="entityname:MusicalRock_et_ltt">
         <color r="255" g="248" b="178">
            <b>Pedra musical do deserto</b>
         </color>
         <br/>
         Clique para selecionar e posicionar uma pedra musical com tema de deserto, que toca música em um alto-falante escondido dentro dela.
      </LOC_STRING>
      <LOC_STRING _locID="entityname:desertfence">Cerca do deserto</LOC_STRING>
      <LOC_STRING _locID="entityname:desertfence_stt">Cerca do deserto</LOC_STRING>
      <LOC_STRING _locID="entityname:desertfence_lower">a cerca do deserto</LOC_STRING>
      <LOC_STRING _locID="entityname:desertfence_ltt">
         <color r="255" g="248" b="178">
            <b>Cerca do deserto</b>
         </color>
         <br/>
         Clique para selecionar e posicionar seções de cerca com tema de deserto. Os visitantes gostam de áreas temáticas no zoológico.
      </LOC_STRING>
      <LOC_STRING _locID="entityname:lowdesert">Cerca baixa do deserto</LOC_STRING>
      <LOC_STRING _locID="entityname:lowdesert_stt">Cerca baixa do deserto</LOC_STRING>
      <LOC_STRING _locID="entityname:lowdesert_lower">a cerca baixa do deserto</LOC_STRING>
      <LOC_STRING _locID="entityname:lowdesert_ltt">
         <color r="255" g="248" b="178">
            <b>Cerca baixa do deserto</b>
         </color>
         <br/>
         Clique para selecionar e posicionar seções de cerca baixa com tema de deserto. Os visitantes gostam de áreas temáticas no zoológico.
      </LOC_STRING>
      <LOC_STRING _locID="entityname:desertwindow">Cerca com janelas do deserto</LOC_STRING>
      <LOC_STRING _locID="entityname:desertwindow_stt">Cerca com janelas do deserto</LOC_STRING>
      <LOC_STRING _locID="entityname:desertwindow_lower">a cerca com janelas do deserto</LOC_STRING>
      <LOC_STRING _locID="entityname:desertwindow_ltt">
         <color r="255" g="248" b="178">
            <b>Cerca com janelas do deserto</b>
         </color>
         <br/>
         Clique para selecionar e posicionar seções de cerca com janelas com tema de deserto. Os visitantes gostam de áreas temáticas no zoológico.
      </LOC_STRING>
      <LOC_STRING _locID="entityname:desert">Trilha do deserto</LOC_STRING>
      <LOC_STRING _locID="entityname:desert_stt">Trilha do deserto</LOC_STRING>
      <LOC_STRING _locID="entityname:desert_lower">a trilha do deserto</LOC_STRING>
      <LOC_STRING _locID="entityname:desert_ltt">
		         <color r="255" g="248" b="178">
		            <b>Trilha do deserto</b>
		         </color>
		         <br/>
		         Clique para selecionar e posicionar seções de trilha com tema de deserto. Os visitantes gostam de áreas temáticas no zoológico.     
      </LOC_STRING>
      <LOC_STRING _locID="zoopedia_desertfence:entry">Cerca do deserto</LOC_STRING>
      <LOC_STRING _locID="zoopedia_desertfence:text">
         <cell pady="0" width="1000"/>
         <p/>
         <cell width="260"/>
         <cell width="640" bgimg="ui/zoopedia/topCellBg.dds">
            <cell width="600" padx="20" pady="20">
               <color r="255" g="255" b="255">
                  <img src="entities\objects\fences\desert_et\desert_et_icon.dds" sx="0" sy="0" sw="64" sh="64"/>
               <p/>O melhor uso de uma cerca com tema de deserto é em jaulas para animais do deserto, como os camelos.
               <p/>Você também pode usar a cerca do deserto para criar áreas públicas temáticas perto das jaulas de deserto. Os visitantes gostam de áreas temáticas.
               </color>
            </cell>
         </cell>
      </LOC_STRING>
      <LOC_STRING _locID="zoopedia_lowdesert:entry">Cerca baixa do deserto</LOC_STRING>
      <LOC_STRING _locID="zoopedia_lowdesert:text">
         <cell pady="0" width="1000"/>
         <p/>
         <cell width="260"/>
         <cell width="640" bgimg="ui/zoopedia/topCellBg.dds">
            <cell width="600" padx="20" pady="20">
               <color r="255" g="255" b="255">
                  <img src="entities\objects\fences\lowdesert_et\lowdesert_et_icon.dds" sx="0" sy="0" sw="64" sh="64"/>
               <p/>O melhor uso de uma cerca com tema de deserto é em jaulas para animais do deserto, como os camelos.
               <p/>Você também pode usar a cerca do deserto para criar áreas públicas temáticas perto das jaulas de deserto. Os visitantes gostam de áreas temáticas.
               </color>
            </cell>
         </cell>
      </LOC_STRING>
      <LOC_STRING _locID="zoopedia_desertwindow:entry">Cerca com janelas do deserto</LOC_STRING>
      <LOC_STRING _locID="zoopedia_desertwindow:text">
         <cell pady="0" width="1000"/>
         <p/>
         <cell width="260"/>
         <cell width="640" bgimg="ui/zoopedia/topCellBg.dds">
            <cell width="600" padx="20" pady="20">
               <color r="255" g="255" b="255">
                  <img src="entities\objects\fences\desertwindow_et\desertwindow_et_icon.dds" sx="0" sy="0" sw="64" sh="64"/>
               <p/>O melhor uso de uma cerca com tema de deserto é em jaulas para animais do deserto, como os camelos.
               <p/>Você também pode usar a cerca do deserto para criar áreas públicas temáticas perto das jaulas de deserto. Os visitantes gostam de áreas temáticas.
               </color>
            </cell>
         </cell>
      </LOC_STRING>
</ZT2Strings>
