<ZT2Strings>
      <LOC_STRING _locID="entityname" version="2"/>
      <LOC_STRING _locID="entityname:Terrain_Insects" version="2">Insekten</LOC_STRING>
      <LOC_STRING _locID="entityname:Terrain_Insects_stt" version="2">Insekten</LOC_STRING>
      <LOC_STRING _locID="entityname:Terrain_Insects_lower" version="2">die Insekten</LOC_STRING>
      <LOC_STRING _locID="entityname:Terrain_Insects_ltt" version="2">
         <color r="255" g="248" b="178">
            <b>Insekten</b>
         </color>
         <br/>
         Klicken Sie hier, um Insekten auszuwählen und zu platzieren. Insekten sind die Nahrungsgrundlage vieler Tiere, z. B. des Erdferkels oder des Erdmännchens.</LOC_STRING>
      <LOC_STRING _locID="entityname:SaltLick" version="2">Salzstein</LOC_STRING>
      <LOC_STRING _locID="entityname:SaltLick_stt" version="2">Salzstein</LOC_STRING>
      <LOC_STRING _locID="entityname:SaltLick_lower" version="2">den Salzstein</LOC_STRING>
      <LOC_STRING _locID="entityname:SaltLick_ltt" version="2">
         <color r="255" g="248" b="178">
            <b>Salzstein</b>
         </color>
         <br/>
         Klicken Sie hier, um einen Salzstein auszuwählen und zu platzieren. Er ist bei allen Huftieren beliebt.
      </LOC_STRING>
   
</ZT2Strings>
