<ZT2Strings>
   <entityname>
      <!--animal names-->
      <StuffedPrey>Beutetierpuppe</StuffedPrey>
      <StuffedPrey_stt>Beutetierpuppe</StuffedPrey_stt>
      <StuffedPrey_lower>die Beutetierpuppe</StuffedPrey_lower>
      <StuffedPrey_ltt>
         <color r="255" g="248" b="178">
            <b>Beutetierpuppe</b>
         </color>
         <br/>
         Klicken Sie hier, um die Beutetierpuppe auszuwählen und zu platzieren. Diese Puppe ist ein Spielzeug für Raubtiere, um das Angreifen von Beute zu üben.
      </StuffedPrey_ltt>
   </entityname>
   <zoopedia_stuffedprey>
      <entry>Beutetierpuppe</entry>
      <text>
         <cell pady="0" width="1000"/>
         <p/>
         <cell width="260"/>
         <cell width="640" height="320" bgimg="ui/zoopedia/topCellBg.dds">
            <cell width="600" padx="20" pady="20">
               <color r="255" g="255" b="255">
                  <p/>
                  <img src="entities\objects\enrichment\StuffedPrey\StuffedPrey_icon.dds" sx="0" sy="0" sw="64" sh="64"/>
                  <p/>Die Beutetierpuppe ist eine aus Stroh und Sackleinen bestehende Puppe in Form einer Gazelle und ist auf einer stabilen Federhalterung montiert.
                  <p/>Fleischfresser mögen es, das Angreifen von Beute durch Beißen oder
               </color>
            </cell>
         </cell>
      </text>
   </zoopedia_stuffedprey>
</ZT2Strings>